{
  "periodico": "El Crisol Republicano: periódico político, literario e industrial",
  "descripcion_objeto": "“El Crisol Republicano: periódico político, literario e industrial” fue una publicación que circuló en Bogotá durante 1881, en su cabezote se incluía el epígrafe “La pluma es un instrumento de propaganda, que ántes de tocar el papel debe pasar por la conciencia, y después de entintada debe empaparse de la buena fé”, el cual era atribuido a “Cárlos Richard”. El título apoyaba la candidatura presidencial del caleño Eliseo Payán, para el periodo 1882-1884 y defendía la idea de la unión liberal, comprendida como “la gran bandera” que debía seguir el partido. Pese a lo mencionado, Payán renunció a la postulación en favor de Francisco Javier Zaldúa, quien resultaría ganador de dicha contienda, con apoyo del partido liberal independiente y el sector conservador. Entre las secciones que componen “El Crisol” se encuentran: “Adhesiones”, “Folletín”, “Ciencias e industria”, “Revista de los Estados”, “Variedades”, “Remitidos”, entre otras. ",
  "collection": "p17054coll26",
  "source_url": "https://babel.banrepcultural.org/digital/collection/p17054coll26/id/17579",
  "child_id": 17578,
  "titulo_numero": "Número 13 - Junio  07 de 1881",
  "year": 1881,
  "download_url": "https://babel.banrepcultural.org/digital/api/collection/p17054coll26/id/17578/download",
  "status": "downloaded_ok",
  "pdf_filename": "ELCRISOLREPUBLICANOPERIODICOPOLITICOLITERARIOEINDUSTRIAL_17578.pdf",
  "created_at": "2026-03-10T23:04:59.605271"
}