{
  "periodico": "La Batalla",
  "descripcion_objeto": "“La Batalla” fue una publicación que circuló en Bogotá durante el periodo 1882-1883. El periódico fue fundado por Juan de Dios Uribe luego de su nombramiento como diputado de la Asamblea del Estado Soberano de Cundinamarca y se estableció como una tribuna de crítica mordaz y recurrente al partido conservador y el partido liberal independiente y su ideal de unión liberal. Además de lo mencionado, Maryluz Vallejo M. (2006), atribuiría el origen de la “crónica parlamentaria” a “La Batalla” y la manera en como Uribe desarrolló sus “crónicas políticas salpicadas de frases incisivas”. En el periódico se reprodujo un anuncio permanente en el que se indicaba que los textos que no fueran del redactor del título se firmarían con una X. Algunas de las secciones más recurrentes de la publicación fueron: la “Batalla” (editorial), “Varia”, “Folletín”, “Los Estados”, “Variedades”, “Colaboradores”, “La Prensa”, “Asamblea” y “Anuncios”-\n\nLas temáticas más relevantes que se atendieron en “La Batalla” se relacionaron con: la posesión y el devenir del gobierno Francisco Javier Zaldúa, el establecimiento de la Liga Anti-clerical en Colombia y la discusión sobre los posibles candidatos que se enfrentarían en las elecciones presidenciales del periodo 1884-1886. Para la citada contienda electoral el periódico apoyó a Solón Wilches, a quién definirían como el más apto para defender los intereses liberales y promover la unión del partido.\n\nEn la sección “Folletín” se reprodujo por entregas “Escenas de la Vida de Bohemia” por Henri Murger.\n",
  "collection": "p17054coll26",
  "source_url": "https://babel.banrepcultural.org/digital/collection/p17054coll26/id/19204",
  "child_id": 19191,
  "titulo_numero": "Número 14 - Enero 27 de 1883",
  "year": 1883,
  "download_url": "https://babel.banrepcultural.org/digital/api/collection/p17054coll26/id/19191/download",
  "status": "downloaded_ok",
  "pdf_filename": "LABATALLA_19191.pdf",
  "created_at": "2026-03-10T23:04:01.745462"
}